{
  "checkpoint": "best",
  "split": "train",
  "prompt_len": 250,
  "max_new_tokens": 2000,
  "min_new_tokens": 2000,
  "num_samples_requested": 10,
  "num_samples_generated": 10,
  "random_offset": false,
  "sampling": {
    "temperature": 0.9,
    "top_k": 160,
    "do_sample": true,
    "stop_on_eos": false
  },
  "samples": [
    {
      "idx": 0,
      "source_json": "C:\\Users\\herre\\PycharmProjects\\TFG_INFO\\data\\interim\\tokenized_finetuning_v2\\Mozart_Wolfgang_Amadeus_Piano_Sonata_No.1_in_C_major_K.279_189d_ZixdOZh7zo4__tr+1__ts1p000.json",
      "prompt_start": 0,
      "prompt_len": 250,
      "generated_len": 2000,
      "hit_eos": false
    },
    {
      "idx": 1,
      "source_json": "C:\\Users\\herre\\PycharmProjects\\TFG_INFO\\data\\interim\\tokenized_finetuning_v2\\Mozart_Wolfgang_Amadeus_Piano_Sonata_No.15_in_F_major_K.533_494_tk9fa1CTY9k__tr-1__ts0p975.json",
      "prompt_start": 0,
      "prompt_len": 250,
      "generated_len": 2000,
      "hit_eos": false
    },
    {
      "idx": 2,
      "source_json": "C:\\Users\\herre\\PycharmProjects\\TFG_INFO\\data\\interim\\tokenized_finetuning_v2\\Mozart_Wolfgang_Amadeus_Sonata_for_Piano_Four-Hands_in_F_major_K.497_t2Aodlo8uKU__tr0__ts1p000.json",
      "prompt_start": 0,
      "prompt_len": 250,
      "generated_len": 2000,
      "hit_eos": false
    },
    {
      "idx": 3,
      "source_json": "C:\\Users\\herre\\PycharmProjects\\TFG_INFO\\data\\interim\\tokenized_finetuning_v2\\Mozart_Wolfgang_Amadeus_Piano_Sonata_No.18_in_D_major_K.576_TfCzqcW0LqE__tr-2__ts0p975.json",
      "prompt_start": 0,
      "prompt_len": 250,
      "generated_len": 2000,
      "hit_eos": false
    },
    {
      "idx": 4,
      "source_json": "C:\\Users\\herre\\PycharmProjects\\TFG_INFO\\data\\interim\\tokenized_finetuning_v2\\Mozart_Wolfgang_Amadeus_Sonata_for_Piano_Four-Hands_in_D_major_K.381_123a_zklTQOUOboY__tr+3__ts0p975.json",
      "prompt_start": 0,
      "prompt_len": 250,
      "generated_len": 2000,
      "hit_eos": false
    },
    {
      "idx": 5,
      "source_json": "C:\\Users\\herre\\PycharmProjects\\TFG_INFO\\data\\interim\\tokenized_finetuning_v2\\Mozart_Wolfgang_Amadeus_Sonata_for_Piano_Four-Hands_in_C_major_K.19d_oTJDS1dprLg__tr+2__ts0p975.json",
      "prompt_start": 0,
      "prompt_len": 250,
      "generated_len": 2000,
      "hit_eos": false
    },
    {
      "idx": 6,
      "source_json": "C:\\Users\\herre\\PycharmProjects\\TFG_INFO\\data\\interim\\tokenized_finetuning_v2\\Mozart_Wolfgang_Amadeus_Sonata_Movement_for_Two_Pianos_K.Anh.42_375b_4oY3lP_i9iA__tr0__ts1p000.json",
      "prompt_start": 0,
      "prompt_len": 250,
      "generated_len": 2000,
      "hit_eos": false
    },
    {
      "idx": 7,
      "source_json": "C:\\Users\\herre\\PycharmProjects\\TFG_INFO\\data\\interim\\tokenized_finetuning_v2\\Mozart_Wolfgang_Amadeus_Sonata_for_Piano_Four-Hands_in_F_major_K.497_t2Aodlo8uKU__tr-3__ts1p050.json",
      "prompt_start": 0,
      "prompt_len": 250,
      "generated_len": 2000,
      "hit_eos": false
    },
    {
      "idx": 8,
      "source_json": "C:\\Users\\herre\\PycharmProjects\\TFG_INFO\\data\\interim\\tokenized_finetuning_v2\\Mozart_Wolfgang_Amadeus_Piano_Sonata_No.20_in_C_minor_8ZyxKd_18G4__tr+2__ts1p025.json",
      "prompt_start": 0,
      "prompt_len": 250,
      "generated_len": 2000,
      "hit_eos": false
    },
    {
      "idx": 9,
      "source_json": "C:\\Users\\herre\\PycharmProjects\\TFG_INFO\\data\\interim\\tokenized_finetuning_v2\\Mozart_Wolfgang_Amadeus_Piano_Sonata_No.11_in_A_major_K.331_300i_vp_h649sZ9A__tr+3__ts0p975.json",
      "prompt_start": 0,
      "prompt_len": 250,
      "generated_len": 2000,
      "hit_eos": false
    }
  ]
}