{
  "update": 5400,
  "sample_id": 2,
  "primer_ids": [
    629,
    630,
    633,
    634,
    653,
    654,
    656,
    658,
    661,
    663,
    175,
    57,
    105,
    113,
    179,
    69,
    104,
    110,
    60,
    104,
    110,
    57,
    103,
    110,
    48,
    102,
    113,
    36,
    101,
    123,
    183,
    67,
    105,
    113,
    60,
    105,
    113,
    57,
    103,
    113,
    51,
    104,
    113,
    39,
    102,
    119,
    187,
    67,
    105,
    115,
    57,
    104,
    113,
    60,
    104,
    113,
    51,
    104,
    115,
    191,
    69,
    106,
    112,
    57,
    105,
    115,
    66,
    105,
    116,
    60,
    105,
    114,
    50,
    104,
    126,
    38,
    104,
    127,
    194,
    71,
    104,
    113,
    195,
    69,
    102,
    111,
    196,
    68,
    104,
    115,
    197,
    69,
    104,
    114,
    199,
    71,
    104,
    111,
    201,
    74,
    105,
    116,
    203,
    72,
    104,
    114,
    205,
    68,
    104,
    112,
    4,
    610,
    611,
    617,
    624,
    626,
    627,
    628,
    629,
    630,
    631,
    632,
    633,
    634,
    653,
    654,
    656,
    658
  ],
  "generated_ids": [
    660,
    663,
    175,
    69,
    105,
    112,
    177,
    71,
    105,
    110,
    570,
    179,
    69,
    104,
    111,
    181,
    67,
    105,
    111,
    183,
    65,
    104,
    111,
    185,
    64,
    104,
    111,
    187,
    74,
    105,
    110,
    570,
    189,
    73,
    104,
    111,
    191,
    69,
    104,
    111,
    193,
    66,
    103,
    110,
    570,
    195,
    67,
    104,
    111,
    197,
    71,
    104,
    111,
    199,
    69,
    103,
    111,
    201,
    67,
    104,
    111,
    203,
    63,
    104,
    111,
    205,
    64,
    103,
    111,
    4,
    610,
    611,
    620,
    624,
    625,
    626,
    627,
    629,
    631,
    633,
    634,
    652,
    654,
    656,
    659,
    660,
    663,
    175,
    62,
    103,
    111,
    177,
    60,
    102,
    110,
    570,
    179,
    59,
    103,
    111,
    181,
    62,
    103,
    111,
    183,
    60,
    102,
    110,
    570,
    185,
    57,
    102,
    111,
    187,
    55,
    103,
    111,
    189,
    54,
    102,
    110,
    570,
    191,
    52,
    103,
    111,
    570,
    194,
    50,
    102,
    111,
    38,
    100,
    110,
    196,
    57,
    103,
    111,
    198,
    55,
    103,
    111,
    200,
    54,
    103,
    111,
    202,
    52,
    102,
    111,
    35,
    101,
    117,
    204,
    55,
    102,
    111,
    4,
    610,
    611,
    618,
    624,
    626,
    627,
    628,
    629,
    631,
    633,
    634,
    652,
    654,
    656,
    658,
    660,
    663,
    174,
    54,
    102,
    111,
    176,
    52,
    102,
    110,
    178,
    50,
    101,
    111,
    179,
    36,
    100,
    143,
    180,
    52,
    102,
    110,
    182,
    54,
    103,
    111,
    184,
    52,
    102,
    111,
    186,
    50,
    102,
    111,
    188,
    48,
    102,
    111,
    189,
    38,
    101,
    132,
    190,
    47,
    103,
    111,
    193,
    48,
    102,
    111,
    195,
    47,
    103,
    111,
    197,
    45,
    103,
    111,
    199,
    43,
    103,
    111,
    201,
    42,
    102,
    111,
    203,
    43,
    103,
    111,
    4,
    610,
    611,
    618,
    627,
    628,
    629,
    630,
    631,
    632,
    633,
    634,
    651,
    654,
    656,
    658,
    661,
    663,
    174,
    42,
    102,
    111,
    176,
    40,
    101,
    110,
    178,
    55,
    102,
    111,
    180,
    42,
    102,
    110,
    570,
    182,
    52,
    102,
    111,
    184,
    49,
    102,
    111,
    185,
    39,
    101,
    134,
    186,
    54,
    103,
    111,
    188,
    52,
    102,
    111,
    190,
    51,
    102,
    111,
    192,
    50,
    103,
    111,
    194,
    48,
    103,
    111,
    196,
    42,
    102,
    113,
    49,
    103,
    111,
    198,
    48,
    103,
    111,
    201,
    49,
    102,
    111,
    203,
    48,
    103,
    111,
    4,
    610,
    611,
    618,
    623,
    624,
    626,
    627,
    629,
    631,
    634,
    652,
    654,
    656,
    658,
    661,
    663,
    174,
    47,
    103,
    111,
    176,
    45,
    102,
    111,
    177,
    55,
    102,
    111,
    179,
    47,
    102,
    111,
    181,
    52,
    102,
    112,
    184,
    47,
    101,
    110,
    185,
    55,
    103,
    102,
    111,
    187,
    57,
    103,
    111,
    189,
    55,
    103,
    111,
    191,
    52,
    102,
    111,
    193,
    50,
    102,
    111,
    195,
    48,
    103,
    111,
    197,
    47,
    103,
    111,
    199,
    48,
    102,
    112,
    201,
    47,
    102,
    111,
    203,
    45,
    102,
    111,
    205,
    44,
    102,
    111,
    4,
    610,
    611,
    620,
    623,
    624,
    626,
    627,
    629,
    630,
    631,
    634,
    653,
    654,
    657,
    658,
    661,
    663,
    175,
    45,
    102,
    111,
    177,
    47,
    103,
    118,
    181,
    56,
    102,
    111,
    183,
    57,
    102,
    110,
    184,
    59,
    102,
    111,
    186,
    60,
    103,
    111,
    188,
    62,
    103,
    111,
    190,
    64,
    103,
    111,
    191,
    59,
    102,
    110,
    570,
    193,
    60,
    103,
    111,
    194,
    57,
    103,
    110,
    570,
    196,
    56,
    102,
    110,
    570,
    198,
    52,
    101,
    110,
    57,
    103,
    111,
    199,
    36,
    100,
    110,
    200,
    45,
    100,
    110,
    201,
    55,
    103,
    111,
    203,
    54,
    103,
    112,
    51,
    101,
    125,
    38,
    100
  ],
  "full_ids": [
    629,
    630,
    633,
    634,
    653,
    654,
    656,
    658,
    661,
    663,
    175,
    57,
    105,
    113,
    179,
    69,
    104,
    110,
    60,
    104,
    110,
    57,
    103,
    110,
    48,
    102,
    113,
    36,
    101,
    123,
    183,
    67,
    105,
    113,
    60,
    105,
    113,
    57,
    103,
    113,
    51,
    104,
    113,
    39,
    102,
    119,
    187,
    67,
    105,
    115,
    57,
    104,
    113,
    60,
    104,
    113,
    51,
    104,
    115,
    191,
    69,
    106,
    112,
    57,
    105,
    115,
    66,
    105,
    116,
    60,
    105,
    114,
    50,
    104,
    126,
    38,
    104,
    127,
    194,
    71,
    104,
    113,
    195,
    69,
    102,
    111,
    196,
    68,
    104,
    115,
    197,
    69,
    104,
    114,
    199,
    71,
    104,
    111,
    201,
    74,
    105,
    116,
    203,
    72,
    104,
    114,
    205,
    68,
    104,
    112,
    4,
    610,
    611,
    617,
    624,
    626,
    627,
    628,
    629,
    630,
    631,
    632,
    633,
    634,
    653,
    654,
    656,
    658,
    660,
    663,
    175,
    69,
    105,
    112,
    177,
    71,
    105,
    110,
    570,
    179,
    69,
    104,
    111,
    181,
    67,
    105,
    111,
    183,
    65,
    104,
    111,
    185,
    64,
    104,
    111,
    187,
    74,
    105,
    110,
    570,
    189,
    73,
    104,
    111,
    191,
    69,
    104,
    111,
    193,
    66,
    103,
    110,
    570,
    195,
    67,
    104,
    111,
    197,
    71,
    104,
    111,
    199,
    69,
    103,
    111,
    201,
    67,
    104,
    111,
    203,
    63,
    104,
    111,
    205,
    64,
    103,
    111,
    4,
    610,
    611,
    620,
    624,
    625,
    626,
    627,
    629,
    631,
    633,
    634,
    652,
    654,
    656,
    659,
    660,
    663,
    175,
    62,
    103,
    111,
    177,
    60,
    102,
    110,
    570,
    179,
    59,
    103,
    111,
    181,
    62,
    103,
    111,
    183,
    60,
    102,
    110,
    570,
    185,
    57,
    102,
    111,
    187,
    55,
    103,
    111,
    189,
    54,
    102,
    110,
    570,
    191,
    52,
    103,
    111,
    570,
    194,
    50,
    102,
    111,
    38,
    100,
    110,
    196,
    57,
    103,
    111,
    198,
    55,
    103,
    111,
    200,
    54,
    103,
    111,
    202,
    52,
    102,
    111,
    35,
    101,
    117,
    204,
    55,
    102,
    111,
    4,
    610,
    611,
    618,
    624,
    626,
    627,
    628,
    629,
    631,
    633,
    634,
    652,
    654,
    656,
    658,
    660,
    663,
    174,
    54,
    102,
    111,
    176,
    52,
    102,
    110,
    178,
    50,
    101,
    111,
    179,
    36,
    100,
    143,
    180,
    52,
    102,
    110,
    182,
    54,
    103,
    111,
    184,
    52,
    102,
    111,
    186,
    50,
    102,
    111,
    188,
    48,
    102,
    111,
    189,
    38,
    101,
    132,
    190,
    47,
    103,
    111,
    193,
    48,
    102,
    111,
    195,
    47,
    103,
    111,
    197,
    45,
    103,
    111,
    199,
    43,
    103,
    111,
    201,
    42,
    102,
    111,
    203,
    43,
    103,
    111,
    4,
    610,
    611,
    618,
    627,
    628,
    629,
    630,
    631,
    632,
    633,
    634,
    651,
    654,
    656,
    658,
    661,
    663,
    174,
    42,
    102,
    111,
    176,
    40,
    101,
    110,
    178,
    55,
    102,
    111,
    180,
    42,
    102,
    110,
    570,
    182,
    52,
    102,
    111,
    184,
    49,
    102,
    111,
    185,
    39,
    101,
    134,
    186,
    54,
    103,
    111,
    188,
    52,
    102,
    111,
    190,
    51,
    102,
    111,
    192,
    50,
    103,
    111,
    194,
    48,
    103,
    111,
    196,
    42,
    102,
    113,
    49,
    103,
    111,
    198,
    48,
    103,
    111,
    201,
    49,
    102,
    111,
    203,
    48,
    103,
    111,
    4,
    610,
    611,
    618,
    623,
    624,
    626,
    627,
    629,
    631,
    634,
    652,
    654,
    656,
    658,
    661,
    663,
    174,
    47,
    103,
    111,
    176,
    45,
    102,
    111,
    177,
    55,
    102,
    111,
    179,
    47,
    102,
    111,
    181,
    52,
    102,
    112,
    184,
    47,
    101,
    110,
    185,
    55,
    103,
    102,
    111,
    187,
    57,
    103,
    111,
    189,
    55,
    103,
    111,
    191,
    52,
    102,
    111,
    193,
    50,
    102,
    111,
    195,
    48,
    103,
    111,
    197,
    47,
    103,
    111,
    199,
    48,
    102,
    112,
    201,
    47,
    102,
    111,
    203,
    45,
    102,
    111,
    205,
    44,
    102,
    111,
    4,
    610,
    611,
    620,
    623,
    624,
    626,
    627,
    629,
    630,
    631,
    634,
    653,
    654,
    657,
    658,
    661,
    663,
    175,
    45,
    102,
    111,
    177,
    47,
    103,
    118,
    181,
    56,
    102,
    111,
    183,
    57,
    102,
    110,
    184,
    59,
    102,
    111,
    186,
    60,
    103,
    111,
    188,
    62,
    103,
    111,
    190,
    64,
    103,
    111,
    191,
    59,
    102,
    110,
    570,
    193,
    60,
    103,
    111,
    194,
    57,
    103,
    110,
    570,
    196,
    56,
    102,
    110,
    570,
    198,
    52,
    101,
    110,
    57,
    103,
    111,
    199,
    36,
    100,
    110,
    200,
    45,
    100,
    110,
    201,
    55,
    103,
    111,
    203,
    54,
    103,
    112,
    51,
    101,
    125,
    38,
    100
  ],
  "temperature": 1.0,
  "top_k": 140
}