{
  "update": 5500,
  "sample_id": 0,
  "primer_ids": [
    654,
    656,
    658,
    660,
    663,
    174,
    62,
    104,
    110,
    571,
    177,
    60,
    104,
    110,
    571,
    180,
    58,
    103,
    118,
    55,
    102,
    118,
    22,
    101,
    111,
    183,
    34,
    102,
    110,
    186,
    24,
    102,
    110,
    188,
    36,
    102,
    110,
    571,
    191,
    56,
    103,
    110,
    53,
    103,
    112,
    26,
    102,
    112,
    192,
    58,
    102,
    112,
    193,
    38,
    102,
    110,
    53,
    100,
    112,
    194,
    56,
    102,
    111,
    195,
    56,
    102,
    110,
    196,
    55,
    102,
    110,
    197,
    39,
    101,
    110,
    51,
    103,
    110,
    570,
    199,
    51,
    103,
    110,
    39,
    101,
    110,
    571,
    202,
    51,
    101,
    110,
    46,
    102,
    110,
    34,
    101,
    110,
    571,
    205,
    39,
    101,
    110,
    51,
    103,
    110,
    4,
    610,
    611,
    620,
    625,
    630,
    634,
    653,
    654,
    656,
    658,
    660,
    663,
    571,
    176,
    43,
    102,
    110,
    31,
    101,
    111,
    51,
    100
  ],
  "generated_ids": [
    110,
    177,
    55,
    101,
    110,
    178,
    39,
    102,
    110,
    51,
    102,
    110,
    571,
    181,
    46,
    103,
    110,
    34,
    100,
    111,
    182,
    31,
    98,
    110,
    27,
    100,
    110,
    51,
    102,
    110,
    55,
    101,
    110,
    570,
    184,
    39,
    102,
    110,
    51,
    102,
    110,
    571,
    187,
    51,
    102,
    110,
    34,
    101,
    110,
    46,
    101,
    110,
    31,
    101,
    110,
    571,
    190,
    46,
    103,
    110,
    34,
    101,
    110,
    571,
    193,
    39,
    103,
    112,
    51,
    103,
    110,
    31,
    100,
    115,
    27,
    101,
    115,
    194,
    34,
    100,
    115,
    196,
    55,
    103,
    112,
    197,
    51,
    101,
    112,
    39,
    100,
    112,
    199,
    58,
    103,
    111,
    55,
    102,
    110,
    570,
    202,
    63,
    103,
    110,
    203,
    58,
    103,
    110,
    570,
    205,
    67,
    103,
    110,
    63,
    102,
    110,
    4,
    610,
    611,
    620,
    623,
    625,
    627,
    629,
    630,
    632,
    634,
    653,
    654,
    656,
    658,
    661,
    663,
    571,
    176,
    62,
    103,
    110,
    58,
    101,
    110,
    65,
    104,
    110,
    177,
    68,
    102,
    110,
    570,
    179,
    63,
    103,
    110,
    67,
    103,
    110,
    51,
    101,
    110,
    39,
    102,
    110,
    571,
    182,
    50,
    101,
    110,
    65,
    104,
    110,
    62,
    102,
    110,
    571,
    185,
    63,
    103,
    110,
    60,
    102,
    110,
    44,
    99,
    110,
    51,
    100,
    110,
    571,
    188,
    51,
    101,
    111,
    39,
    102,
    110,
    570,
    191,
    38,
    102,
    110,
    62,
    102,
    110,
    58,
    101,
    110,
    570,
    193,
    27,
    101,
    110,
    194,
    63,
    102,
    110,
    60,
    101,
    110,
    51,
    100,
    110,
    39,
    101,
    110,
    571,
    197,
    38,
    100,
    112,
    50,
    100,
    115,
    58,
    101,
    112,
    200,
    58,
    99,
    112,
    38,
    99,
    112,
    203,
    38,
    98,
    112,
    50,
    97,
    113,
    4,
    610,
    611,
    619,
    625,
    629,
    630,
    634,
    653,
    654,
    656,
    658,
    661,
    663,
    174,
    38,
    96,
    110,
    572,
    178,
    38,
    95,
    110,
    58,
    99,
    111,
    55,
    99,
    116,
    179,
    43,
    98,
    111,
    46,
    97,
    112,
    39,
    98,
    114,
    181,
    43,
    97,
    112,
    46,
    96,
    112,
    182,
    58,
    97,
    118,
    184,
    46,
    99,
    115,
    43,
    97,
    112,
    39,
    97,
    111,
    187,
    43,
    97,
    112,
    39,
    97,
    112,
    190,
    43,
    97,
    113,
    46,
    97,
    111,
    39,
    97,
    111,
    193,
    46,
    96,
    110,
    55,
    98,
    113,
    39,
    97,
    115,
    196,
    55,
    101,
    112,
    43,
    98,
    112,
    199,
    58,
    101,
    112,
    43,
    98,
    112,
    200,
    55,
    99,
    112,
    39,
    97,
    112,
    202,
    58,
    101,
    112,
    43,
    98,
    112,
    203,
    39,
    98,
    115,
    205,
    58,
    101,
    112,
    43,
    99,
    112,
    4,
    610,
    611,
    620,
    625,
    627,
    628,
    630,
    631,
    634,
    653,
    654,
    656,
    659,
    661,
    663,
    174,
    46,
    97,
    112,
    176,
    58,
    102,
    112,
    177,
    46,
    98,
    112,
    39,
    97,
    112,
    43,
    98,
    111,
    179,
    58,
    101,
    112,
    43,
    100,
    112,
    39,
    98,
    117,
    46,
    98,
    112,
    182,
    58,
    102,
    112,
    43,
    100,
    111,
    46,
    98,
    110,
    185,
    61,
    102,
    110,
    43,
    99,
    111,
    46,
    98,
    110,
    187,
    43,
    100,
    112,
    61,
    102,
    112,
    46,
    98,
    112,
    39,
    98,
    112,
    190,
    43,
    100,
    110,
    61,
    103,
    112,
    46,
    98,
    114,
    39,
    98,
    114,
    193,
    43,
    100,
    112,
    61,
    103,
    112,
    195,
    46,
    98,
    110,
    196,
    43,
    100,
    111,
    39,
    98,
    113,
    61,
    102,
    110,
    197,
    43,
    99,
    114,
    199,
    46,
    100,
    112,
    60,
    103,
    112,
    39,
    100,
    115,
    202,
    43,
    100,
    112,
    60,
    103,
    112,
    46,
    99
  ],
  "full_ids": [
    654,
    656,
    658,
    660,
    663,
    174,
    62,
    104,
    110,
    571,
    177,
    60,
    104,
    110,
    571,
    180,
    58,
    103,
    118,
    55,
    102,
    118,
    22,
    101,
    111,
    183,
    34,
    102,
    110,
    186,
    24,
    102,
    110,
    188,
    36,
    102,
    110,
    571,
    191,
    56,
    103,
    110,
    53,
    103,
    112,
    26,
    102,
    112,
    192,
    58,
    102,
    112,
    193,
    38,
    102,
    110,
    53,
    100,
    112,
    194,
    56,
    102,
    111,
    195,
    56,
    102,
    110,
    196,
    55,
    102,
    110,
    197,
    39,
    101,
    110,
    51,
    103,
    110,
    570,
    199,
    51,
    103,
    110,
    39,
    101,
    110,
    571,
    202,
    51,
    101,
    110,
    46,
    102,
    110,
    34,
    101,
    110,
    571,
    205,
    39,
    101,
    110,
    51,
    103,
    110,
    4,
    610,
    611,
    620,
    625,
    630,
    634,
    653,
    654,
    656,
    658,
    660,
    663,
    571,
    176,
    43,
    102,
    110,
    31,
    101,
    111,
    51,
    100,
    110,
    177,
    55,
    101,
    110,
    178,
    39,
    102,
    110,
    51,
    102,
    110,
    571,
    181,
    46,
    103,
    110,
    34,
    100,
    111,
    182,
    31,
    98,
    110,
    27,
    100,
    110,
    51,
    102,
    110,
    55,
    101,
    110,
    570,
    184,
    39,
    102,
    110,
    51,
    102,
    110,
    571,
    187,
    51,
    102,
    110,
    34,
    101,
    110,
    46,
    101,
    110,
    31,
    101,
    110,
    571,
    190,
    46,
    103,
    110,
    34,
    101,
    110,
    571,
    193,
    39,
    103,
    112,
    51,
    103,
    110,
    31,
    100,
    115,
    27,
    101,
    115,
    194,
    34,
    100,
    115,
    196,
    55,
    103,
    112,
    197,
    51,
    101,
    112,
    39,
    100,
    112,
    199,
    58,
    103,
    111,
    55,
    102,
    110,
    570,
    202,
    63,
    103,
    110,
    203,
    58,
    103,
    110,
    570,
    205,
    67,
    103,
    110,
    63,
    102,
    110,
    4,
    610,
    611,
    620,
    623,
    625,
    627,
    629,
    630,
    632,
    634,
    653,
    654,
    656,
    658,
    661,
    663,
    571,
    176,
    62,
    103,
    110,
    58,
    101,
    110,
    65,
    104,
    110,
    177,
    68,
    102,
    110,
    570,
    179,
    63,
    103,
    110,
    67,
    103,
    110,
    51,
    101,
    110,
    39,
    102,
    110,
    571,
    182,
    50,
    101,
    110,
    65,
    104,
    110,
    62,
    102,
    110,
    571,
    185,
    63,
    103,
    110,
    60,
    102,
    110,
    44,
    99,
    110,
    51,
    100,
    110,
    571,
    188,
    51,
    101,
    111,
    39,
    102,
    110,
    570,
    191,
    38,
    102,
    110,
    62,
    102,
    110,
    58,
    101,
    110,
    570,
    193,
    27,
    101,
    110,
    194,
    63,
    102,
    110,
    60,
    101,
    110,
    51,
    100,
    110,
    39,
    101,
    110,
    571,
    197,
    38,
    100,
    112,
    50,
    100,
    115,
    58,
    101,
    112,
    200,
    58,
    99,
    112,
    38,
    99,
    112,
    203,
    38,
    98,
    112,
    50,
    97,
    113,
    4,
    610,
    611,
    619,
    625,
    629,
    630,
    634,
    653,
    654,
    656,
    658,
    661,
    663,
    174,
    38,
    96,
    110,
    572,
    178,
    38,
    95,
    110,
    58,
    99,
    111,
    55,
    99,
    116,
    179,
    43,
    98,
    111,
    46,
    97,
    112,
    39,
    98,
    114,
    181,
    43,
    97,
    112,
    46,
    96,
    112,
    182,
    58,
    97,
    118,
    184,
    46,
    99,
    115,
    43,
    97,
    112,
    39,
    97,
    111,
    187,
    43,
    97,
    112,
    39,
    97,
    112,
    190,
    43,
    97,
    113,
    46,
    97,
    111,
    39,
    97,
    111,
    193,
    46,
    96,
    110,
    55,
    98,
    113,
    39,
    97,
    115,
    196,
    55,
    101,
    112,
    43,
    98,
    112,
    199,
    58,
    101,
    112,
    43,
    98,
    112,
    200,
    55,
    99,
    112,
    39,
    97,
    112,
    202,
    58,
    101,
    112,
    43,
    98,
    112,
    203,
    39,
    98,
    115,
    205,
    58,
    101,
    112,
    43,
    99,
    112,
    4,
    610,
    611,
    620,
    625,
    627,
    628,
    630,
    631,
    634,
    653,
    654,
    656,
    659,
    661,
    663,
    174,
    46,
    97,
    112,
    176,
    58,
    102,
    112,
    177,
    46,
    98,
    112,
    39,
    97,
    112,
    43,
    98,
    111,
    179,
    58,
    101,
    112,
    43,
    100,
    112,
    39,
    98,
    117,
    46,
    98,
    112,
    182,
    58,
    102,
    112,
    43,
    100,
    111,
    46,
    98,
    110,
    185,
    61,
    102,
    110,
    43,
    99,
    111,
    46,
    98,
    110,
    187,
    43,
    100,
    112,
    61,
    102,
    112,
    46,
    98,
    112,
    39,
    98,
    112,
    190,
    43,
    100,
    110,
    61,
    103,
    112,
    46,
    98,
    114,
    39,
    98,
    114,
    193,
    43,
    100,
    112,
    61,
    103,
    112,
    195,
    46,
    98,
    110,
    196,
    43,
    100,
    111,
    39,
    98,
    113,
    61,
    102,
    110,
    197,
    43,
    99,
    114,
    199,
    46,
    100,
    112,
    60,
    103,
    112,
    39,
    100,
    115,
    202,
    43,
    100,
    112,
    60,
    103,
    112,
    46,
    99
  ],
  "temperature": 1.0,
  "top_k": 140
}