{
  "checkpoint": "best",
  "split": "train",
  "prompt_len": 150,
  "max_new_tokens": 4000,
  "min_new_tokens": 2000,
  "num_samples_requested": 5,
  "num_samples_generated": 5,
  "random_offset": true,
  "sampling": {
    "temperature": 0.9,
    "top_k": 120,
    "do_sample": true,
    "stop_on_eos": true
  },
  "samples": [
    {
      "idx": 0,
      "source_json": "C:\\Users\\herre\\PycharmProjects\\TFG_INFO\\data\\interim\\tokenized_json_bpe_v2\\ariamidi\\id\\422259_0.json",
      "prompt_start": 0,
      "prompt_len": 150,
      "generated_len": 4000,
      "hit_eos": false
    },
    {
      "idx": 1,
      "source_json": "C:\\Users\\herre\\PycharmProjects\\TFG_INFO\\data\\interim\\tokenized_json_bpe_v2\\ariamidi\\gu\\353340_0.json",
      "prompt_start": 0,
      "prompt_len": 150,
      "generated_len": 4000,
      "hit_eos": false
    },
    {
      "idx": 2,
      "source_json": "C:\\Users\\herre\\PycharmProjects\\TFG_INFO\\data\\interim\\tokenized_json_bpe_v2\\ariamidi\\da\\156403_0.json",
      "prompt_start": 0,
      "prompt_len": 150,
      "generated_len": 2496,
      "hit_eos": true
    },
    {
      "idx": 3,
      "source_json": "C:\\Users\\herre\\PycharmProjects\\TFG_INFO\\data\\interim\\tokenized_json_bpe_v2\\ariamidi\\bv\\095405_0.json",
      "prompt_start": 0,
      "prompt_len": 150,
      "generated_len": 4000,
      "hit_eos": false
    },
    {
      "idx": 4,
      "source_json": "C:\\Users\\herre\\PycharmProjects\\TFG_INFO\\data\\interim\\tokenized_json_bpe_v2\\ariamidi\\ds\\193817_0.json",
      "prompt_start": 0,
      "prompt_len": 150,
      "generated_len": 4000,
      "hit_eos": false
    }
  ]
}